airflow/providers/oracle/__init__.py
airflow/providers/oracle/get_provider_info.py
airflow/providers/oracle/version_compat.py
airflow/providers/oracle/example_dags/__init__.py
airflow/providers/oracle/example_dags/example_oracle.py
airflow/providers/oracle/example_dags/example_oracle_fetch.py
airflow/providers/oracle/hooks/__init__.py
airflow/providers/oracle/hooks/oracle.py
airflow/providers/oracle/operators/__init__.py
airflow/providers/oracle/operators/oracle.py
airflow/providers/oracle/transfers/__init__.py
airflow/providers/oracle/transfers/oracle_to_oracle.py
apache_airflow_providers_oracle-4.3.1.dist-info/entry_points.txt
apache_airflow_providers_oracle-4.3.1.dist-info/licenses/LICENSE
apache_airflow_providers_oracle-4.3.1.dist-info/licenses/NOTICE
apache_airflow_providers_oracle-4.3.1.dist-info/WHEEL
apache_airflow_providers_oracle-4.3.1.dist-info/METADATA
apache_airflow_providers_oracle-4.3.1.dist-info/RECORD
